[
  {
    "Name": "Mike McCool",
    "Address": "5423 Laguana Suerte Santa-Tresa, NM 88610",
    "Phone": "(575)720-4576",
    "Orders": null
  },
  {
    "Name": "mark belto",
    "Address": "1230 bluemel",
    "Phone": "999-0000",
    "Orders": null
  },
  {
    "Name": "Dan Meridith",
    "Address": "7 Monday Night Football",
    "Phone": "(909)567-4198",
    "Orders": null
  },
  {
    "Name":"Ron",
    "Address": "894 Wilson Ave.",
    "Phone": "(210)989-3227",
    "Orders": null
  },
  {
    "Name": "Jill Wilson",
    "Address": "444 hue st.",
    "Phone": "(878)221-4387",
    "Orders": null
  },
  {
    "Name": "55555",
    "Address": "5555555",
    "Phone": "5555555",
    "Orders": null
  }
]